nortax/__init__.py
nortax/constants/__init__.py
nortax/constants/misc.py
nortax/eks.py
nortax/models/__init__.py
nortax/models/custom_types.py
nortax/nortax.py
nortax-0.1.0.dist-info/LICENSE
nortax-0.1.0.dist-info/METADATA
nortax-0.1.0.dist-info/WHEEL
nortax-0.1.0.dist-info/RECORD
