Metadata-Version: 2.1
Name: nortax
Version: 0.1.0
Summary: A Python client for the tax table portion of the Norwegian tax authority's API
Home-page: https://github.com/lewiuberg/nortax
Keywords: tax,norway,api,client,tax table,tax authority,nortax
Author: Lewi Uberg
Author-email: lewiuberg@icloud.com
Maintainer: Lewi Uberg
Maintainer-email: lewiuberg@icloud.com
Requires-Python: >=3.11.1,<4.0.0
Classifier: Development Status :: 3 - Alpha
Classifier: Intended Audience :: Developers
Classifier: License :: OSI Approved :: MIT License
Classifier: Programming Language :: Python :: 3
Classifier: Programming Language :: Python :: 3.11
Classifier: Topic :: Software Development :: Libraries :: Python Modules
Requires-Dist: requests (>=2.31.0,<3.0.0)
Project-URL: Documentation, https://github.com/lewiuberg/nortax/blob/main/README.md
Project-URL: Repository, https://github.com/lewiuberg/nortax
